{
  "story": {
    "id": "story_1756430328_6",
    "title": "Finn and the Friendly Dragon",
    "summary": "Little Emma discovers a lonely dragon in the forest and helps him find a new home where he can be happy and make friends.",
    "scenes": [
      "Finn walking through the enchanted forest picking flowers",
      "Finn discovering a sad dragon hiding behind a large tree",
      "Finn and the dragon sitting together as she listens to his problem",
      "The dragon showing Finn his old cave that became too small",
      "Finn and the dragon searching for a perfect new home together",
      "They find a beautiful mountain cave with a crystal lake",
      "Finn helping the dragon decorate his new cave with colorful gems",
      "The dragon practicing flying around his new mountain home",
      "Village children meeting the friendly dragon for the first time",
      "The dragon giving the children rides around the mountain",
      "Finn and friends having a picnic with the dragon by the lake",
      "The dragon teaching the children about nature and magic",
      "Everyone working together to plant a beautiful garden",
      "The dragon using his fire breath to help cook a feast",
      "All the forest animals coming to welcome the dragon",
      "The dragon and Finn reading stories under the stars",
      "The dragon protecting the village from a terrible storm",
      "The grateful villagers throwing a celebration party",
      "Finn and the dragon watching the sunset from the mountain top",
      "The dragon and all his new friends living happily together"
    ],
    "theme": "dragon_friendship",
    "target_age": "5-8",
    "art_style": {
      "name": "Cartoon",
      "coloring_style": "cartoon style black and white line art, bold clean lines",
      "cover_style": "cartoon style with bright primary colors, fun cartoon cover",
      "complexity": "simple bold clean lines perfect for young children"
    },
    "main_character": "Finn",
    "companion": "Hopper the Rabbit",
    "generated_at": "2025-08-29T03:18:48.276509",
    "page_count": 20,
    "consistent_character": true,
    "story_type": "complete_narrative"
  },
  "generation_info": {
    "generated_at": "2025-08-29T04:36:34.246310",
    "pdf_path": "automated_books\\Finn_and_the_Friendly_Dragon_Cartoon_20250829_043633.pdf",
    "total_prompts": 21,
    "successful_images": 21,
    "failed_images": 0,
    "pipeline_version": "2.0_improved_stories_clean_lines"
  },
  "stats": {
    "stories_generated": 7,
    "images_generated": 147,
    "pdfs_created": 7,
    "errors": 0,
    "start_time": "2025-08-28T16:17:13.246323",
    "last_generation": "2025-08-29T03:18:48.277055"
  }
}